hpm/__init__.py
hpm/__main__.py
hpm/_printing.py
hpm/_typing.py
hpm/api.py
hpm/cli_args.py
hpm/errors.py
hpm/hpm.py
hpm/namespaces.py
hpm/commands/CloneCommand.py
hpm/commands/CreateAppCommand.py
hpm/commands/ListCommand.py
hpm/commands/SetupCommand.py
hpm/commands/__init__.py
hpm/commands/constants.py
hpm/questions/__init__.py
hpm/questions/project.py
hpm-0.4.1.dist-info/LICENSE
hpm-0.4.1.dist-info/METADATA
hpm-0.4.1.dist-info/WHEEL
hpm-0.4.1.dist-info/entry_points.txt
hpm-0.4.1.dist-info/top_level.txt
hpm-0.4.1.dist-info/RECORD
