Metadata-Version: 2.1
Name: hpm
Version: 0.4.1
Summary: HEPIA Project Manager
Home-page: https://gitedu.hesge.ch/tanguy.cavagna/hpm
Author: Tanguy Cavagna
Author-email: tanguy.cvgn@gmail.com
License: UNKNOWN
Project-URL: Bug Tracker, https://gitedu.hesge.ch/tanguy.cavagna/hpm/-/issues
Platform: UNKNOWN
Classifier: Programming Language :: Python :: 3
Classifier: License :: OSI Approved :: MIT License
Classifier: Operating System :: OS Independent
Requires-Python: >=3.6
License-File: LICENSE
Requires-Dist: requests
Requires-Dist: rich
